dqclibs/__init__.py
dqclibs/_version.py
dqclibs/_version.txt
dqclibs/api.py
dqclibs/libcgto.dylib
dqclibs/libcint.4.0.7.dylib
dqclibs/libcint.4.dylib
dqclibs/libcint.dylib
dqclibs/libcvhf.dylib
dqclibs/libnp_helper.dylib
dqclibs/libpbc.dylib
dqclibs/libsymm.dylib
dqclibs/libs/__init__.py
dqclibs/tests/__init__.py
dqclibs/tests/test_libs.py
dqclibs-0.1.1.dist-info/LICENSE
dqclibs-0.1.1.dist-info/METADATA
dqclibs-0.1.1.dist-info/WHEEL
dqclibs-0.1.1.dist-info/top_level.txt
dqclibs-0.1.1.dist-info/RECORD
